{"items":[{"ID":1,"Type":"BG","Position":"0,0,0","Rotation":"0,0,0","Scale":"1,1,1","Json":"{}"},{"ID":2,"Type":"Ground","Position":"0,-4.5,0","Rotation":"0,0,0","Scale":"1,1,1","Json":"{\"Type\":26}"},{"ID":3,"Type":"Ground","Position":"-7.2,-2.7,0","Rotation":"0,0,0","Scale":"1,1,1","Json":"{\"Type\":3}"},{"ID":4,"Type":"Brick","Position":"6.818,-2.946,0","Rotation":"0,0,0","Scale":"0.6,0.6,1","Json":"{\"Type\":6,\"Tag\":\"WoodObject\",\"Hp\":8.25,\"Score\":10000,\"Mass\":2,\"AngularDrag\":0.05,\"GravityScale\":1}"},{"ID":5,"Type":"Brick","Position":"6.41,-2.946,0","Rotation":"0,0,0","Scale":"0.6,0.6,1","Json":"{\"Type\":6,\"Tag\":\"WoodObject\",\"Hp\":8.25,\"Score\":10000,\"Mass\":2,\"AngularDrag\":0.05,\"GravityScale\":1}"},{"ID":6,"Type":"Brick","Position":"6.818,-2.538,0","Rotation":"0,0,0","Scale":"0.6,0.6,1","Json":"{\"Type\":6,\"Tag\":\"WoodObject\",\"Hp\":8.25,\"Score\":10000,\"Mass\":2,\"AngularDrag\":0.05,\"GravityScale\":1}"},{"ID":7,"Type":"Brick","Position":"6.41,-2.538,0","Rotation":"0,0,0","Scale":"0.6,0.6,1","Json":"{\"Type\":6,\"Tag\":\"WoodObject\",\"Hp\":8.25,\"Score\":10000,\"Mass\":2,\"AngularDrag\":0.05,\"GravityScale\":1}"},{"ID":8,"Type":"Brick","Position":"6.818,-2.13,0","Rotation":"0,0,0","Scale":"0.6,0.6,1","Json":"{\"Type\":6,\"Tag\":\"WoodObject\",\"Hp\":8.25,\"Score\":10000,\"Mass\":2,\"AngularDrag\":0.05,\"GravityScale\":1}"},{"ID":9,"Type":"Brick","Position":"6.41,-2.13,0","Rotation":"0,0,0","Scale":"0.6,0.6,1","Json":"{\"Type\":6,\"Tag\":\"WoodObject\",\"Hp\":8.25,\"Score\":10000,\"Mass\":2,\"AngularDrag\":0.05,\"GravityScale\":1}"},{"ID":10,"Type":"Brick","Position":"6.818,-1.722,0","Rotation":"0,0,0","Scale":"0.6,0.6,1","Json":"{\"Type\":6,\"Tag\":\"WoodObject\",\"Hp\":8.25,\"Score\":10000,\"Mass\":2,\"AngularDrag\":0.05,\"GravityScale\":1}"},{"ID":11,"Type":"Brick","Position":"6.41,-1.722,0","Rotation":"0,0,0","Scale":"0.6,0.6,1","Json":"{\"Type\":6,\"Tag\":\"WoodObject\",\"Hp\":8.25,\"Score\":10000,\"Mass\":2,\"AngularDrag\":0.05,\"GravityScale\":1}"},{"ID":12,"Type":"Brick","Position":"6.818,-1.314,0","Rotation":"0,0,0","Scale":"0.6,0.6,1","Json":"{\"Type\":6,\"Tag\":\"WoodObject\",\"Hp\":8.25,\"Score\":10000,\"Mass\":2,\"AngularDrag\":0.05,\"GravityScale\":1}"},{"ID":13,"Type":"Brick","Position":"6.41,-1.314,0","Rotation":"0,0,0","Scale":"0.6,0.6,1","Json":"{\"Type\":6,\"Tag\":\"WoodObject\",\"Hp\":8.25,\"Score\":10000,\"Mass\":2,\"AngularDrag\":0.05,\"GravityScale\":1}"},{"ID":14,"Type":"Brick","Position":"6.818,-0.906,0","Rotation":"0,0,0","Scale":"0.6,0.6,1","Json":"{\"Type\":6,\"Tag\":\"WoodObject\",\"Hp\":8.25,\"Score\":10000,\"Mass\":2,\"AngularDrag\":0.05,\"GravityScale\":1}"},{"ID":15,"Type":"Brick","Position":"6.41,-0.906,0","Rotation":"0,0,0","Scale":"0.6,0.6,1","Json":"{\"Type\":6,\"Tag\":\"WoodObject\",\"Hp\":8.25,\"Score\":10000,\"Mass\":2,\"AngularDrag\":0.05,\"GravityScale\":1}"},{"ID":16,"Type":"Brick","Position":"6.818,-0.498,0","Rotation":"0,0,0","Scale":"0.6,0.6,1","Json":"{\"Type\":6,\"Tag\":\"WoodObject\",\"Hp\":8.25,\"Score\":10000,\"Mass\":2,\"AngularDrag\":0.05,\"GravityScale\":1}"},{"ID":17,"Type":"Brick","Position":"6.41,-0.498,0","Rotation":"0,0,0","Scale":"0.6,0.6,1","Json":"{\"Type\":6,\"Tag\":\"WoodObject\",\"Hp\":8.25,\"Score\":10000,\"Mass\":2,\"AngularDrag\":0.05,\"GravityScale\":1}"},{"ID":18,"Type":"Brick","Position":"6.818,-0.09000003,0","Rotation":"0,0,0","Scale":"0.6,0.6,1","Json":"{\"Type\":6,\"Tag\":\"WoodObject\",\"Hp\":8.25,\"Score\":10000,\"Mass\":2,\"AngularDrag\":0.05,\"GravityScale\":1}"},{"ID":19,"Type":"Brick","Position":"6.41,-0.09000003,0","Rotation":"0,0,0","Scale":"0.6,0.6,1","Json":"{\"Type\":6,\"Tag\":\"WoodObject\",\"Hp\":8.25,\"Score\":10000,\"Mass\":2,\"AngularDrag\":0.05,\"GravityScale\":1}"},{"ID":20,"Type":"Brick","Position":"5.816,-1.404,0","Rotation":"0,0,0","Scale":"0.6,0.6,1","Json":"{\"Type\":1,\"Tag\":\"WoodObject\",\"Hp\":8.25,\"Score\":9600,\"Mass\":2,\"AngularDrag\":0.05,\"GravityScale\":1}"},{"ID":21,"Type":"Brick","Position":"5.816,-1.176,0","Rotation":"0,0,0","Scale":"0.6,0.6,1","Json":"{\"Type\":1,\"Tag\":\"WoodObject\",\"Hp\":8.25,\"Score\":9600,\"Mass\":2,\"AngularDrag\":0.05,\"GravityScale\":1}"},{"ID":22,"Type":"Brick","Position":"5.816,-0.948,0","Rotation":"0,0,0","Scale":"0.6,0.6,1","Json":"{\"Type\":1,\"Tag\":\"WoodObject\",\"Hp\":8.25,\"Score\":9600,\"Mass\":2,\"AngularDrag\":0.05,\"GravityScale\":1}"},{"ID":23,"Type":"Brick","Position":"6.002,-0.6300001,0","Rotation":"0,0,0","Scale":"0.6,0.6,1","Json":"{\"Type\":6,\"Tag\":\"WoodObject\",\"Hp\":8.25,\"Score\":10000,\"Mass\":2,\"AngularDrag\":0.05,\"GravityScale\":1}"},{"ID":24,"Type":"Brick","Position":"5.594,-0.6300001,0","Rotation":"0,0,0","Scale":"0.6,0.6,1","Json":"{\"Type\":6,\"Tag\":\"WoodObject\",\"Hp\":8.25,\"Score\":10000,\"Mass\":2,\"AngularDrag\":0.05,\"GravityScale\":1}"},{"ID":25,"Type":"Brick","Position":"6.002,-0.222,0","Rotation":"0,0,0","Scale":"0.6,0.6,1","Json":"{\"Type\":6,\"Tag\":\"WoodObject\",\"Hp\":8.25,\"Score\":10000,\"Mass\":2,\"AngularDrag\":0.05,\"GravityScale\":1}"},{"ID":26,"Type":"Brick","Position":"5.594,-0.222,0","Rotation":"0,0,0","Scale":"0.6,0.6,1","Json":"{\"Type\":6,\"Tag\":\"WoodObject\",\"Hp\":8.25,\"Score\":10000,\"Mass\":2,\"AngularDrag\":0.05,\"GravityScale\":1}"},{"ID":27,"Type":"Brick","Position":"6.002,0.186,0","Rotation":"0,0,0","Scale":"0.6,0.6,1","Json":"{\"Type\":6,\"Tag\":\"WoodObject\",\"Hp\":8.25,\"Score\":10000,\"Mass\":2,\"AngularDrag\":0.05,\"GravityScale\":1}"},{"ID":28,"Type":"Brick","Position":"5.594,0.186,0","Rotation":"0,0,0","Scale":"0.6,0.6,1","Json":"{\"Type\":6,\"Tag\":\"WoodObject\",\"Hp\":8.25,\"Score\":10000,\"Mass\":2,\"AngularDrag\":0.05,\"GravityScale\":1}"},{"ID":29,"Type":"Brick","Position":"6.002,0.594,0","Rotation":"0,0,0","Scale":"0.6,0.6,1","Json":"{\"Type\":6,\"Tag\":\"WoodObject\",\"Hp\":8.25,\"Score\":10000,\"Mass\":2,\"AngularDrag\":0.05,\"GravityScale\":1}"},{"ID":30,"Type":"Brick","Position":"5.594,0.594,0","Rotation":"0,0,0","Scale":"0.6,0.6,1","Json":"{\"Type\":6,\"Tag\":\"WoodObject\",\"Hp\":8.25,\"Score\":10000,\"Mass\":2,\"AngularDrag\":0.05,\"GravityScale\":1}"},{"ID":31,"Type":"Brick","Position":"6.002,1.002,0","Rotation":"0,0,0","Scale":"0.6,0.6,1","Json":"{\"Type\":6,\"Tag\":\"WoodObject\",\"Hp\":8.25,\"Score\":10000,\"Mass\":2,\"AngularDrag\":0.05,\"GravityScale\":1}"},{"ID":32,"Type":"Brick","Position":"5.594,1.002,0","Rotation":"0,0,0","Scale":"0.6,0.6,1","Json":"{\"Type\":6,\"Tag\":\"WoodObject\",\"Hp\":8.25,\"Score\":10000,\"Mass\":2,\"AngularDrag\":0.05,\"GravityScale\":1}"},{"ID":33,"Type":"Brick","Position":"5.186,-1.314,0","Rotation":"0,0,0","Scale":"0.6,0.6,1","Json":"{\"Type\":6,\"Tag\":\"WoodObject\",\"Hp\":8.25,\"Score\":10000,\"Mass\":2,\"AngularDrag\":0.05,\"GravityScale\":1}"},{"ID":34,"Type":"Brick","Position":"4.64,-1.014,0","Rotation":"0,0,0","Scale":"0.6,0.6,1","Json":"{\"Type\":2,\"Tag\":\"WoodObject\",\"Hp\":8.25,\"Score\":9650,\"Mass\":2,\"AngularDrag\":0.05,\"GravityScale\":1}"},{"ID":35,"Type":"Brick","Position":"4.64,-0.822,0","Rotation":"0,0,0","Scale":"0.6,0.6,1","Json":"{\"Type\":2,\"Tag\":\"WoodObject\",\"Hp\":8.25,\"Score\":9650,\"Mass\":2,\"AngularDrag\":0.05,\"GravityScale\":1}"},{"ID":36,"Type":"Brick","Position":"4.5,-0.138,0","Rotation":"0,0,0","Scale":"0.6,0.6,1","Json":"{\"Type\":6,\"Tag\":\"WoodObject\",\"Hp\":8.25,\"Score\":10000,\"Mass\":2,\"AngularDrag\":0.05,\"GravityScale\":1}"},{"ID":37,"Type":"Brick","Position":"4.092,-0.138,0","Rotation":"0,0,0","Scale":"0.6,0.6,1","Json":"{\"Type\":6,\"Tag\":\"WoodObject\",\"Hp\":8.25,\"Score\":10000,\"Mass\":2,\"AngularDrag\":0.05,\"GravityScale\":1}"},{"ID":38,"Type":"Brick","Position":"4.5,0.27,0","Rotation":"0,0,0","Scale":"0.6,0.6,1","Json":"{\"Type\":6,\"Tag\":\"WoodObject\",\"Hp\":8.25,\"Score\":10000,\"Mass\":2,\"AngularDrag\":0.05,\"GravityScale\":1}"},{"ID":39,"Type":"Brick","Position":"4.092,0.27,0","Rotation":"0,0,0","Scale":"0.6,0.6,1","Json":"{\"Type\":6,\"Tag\":\"WoodObject\",\"Hp\":8.25,\"Score\":10000,\"Mass\":2,\"AngularDrag\":0.05,\"GravityScale\":1}"},{"ID":40,"Type":"Brick","Position":"3.318,-1.994,0","Rotation":"0,0,90","Scale":"0.6,0.6,1","Json":"{\"Type\":1,\"Tag\":\"WoodObject\",\"Hp\":8.25,\"Score\":9600,\"Mass\":2,\"AngularDrag\":0.05,\"GravityScale\":1}"},{"ID":41,"Type":"Brick","Position":"3.776,-1.994,0","Rotation":"0,0,90","Scale":"0.6,0.6,1","Json":"{\"Type\":1,\"Tag\":\"WoodObject\",\"Hp\":8.25,\"Score\":9600,\"Mass\":2,\"AngularDrag\":0.05,\"GravityScale\":1}"},{"ID":42,"Type":"Brick","Position":"3.548,-1.994,0","Rotation":"0,0,90","Scale":"0.6,0.6,1","Json":"{\"Type\":1,\"Tag\":\"WoodObject\",\"Hp\":8.25,\"Score\":9600,\"Mass\":2,\"AngularDrag\":0.05,\"GravityScale\":1}"},{"ID":43,"Type":"Brick","Position":"3.548,-2.498,0","Rotation":"0,0,0","Scale":"0.6,0.6,1","Json":"{\"Type\":1,\"Tag\":\"WoodObject\",\"Hp\":8.25,\"Score\":9600,\"Mass\":2,\"AngularDrag\":0.05,\"GravityScale\":1}"},{"ID":44,"Type":"Brick","Position":"3.548,-2.726,0","Rotation":"0,0,0","Scale":"0.6,0.6,1","Json":"{\"Type\":1,\"Tag\":\"WoodObject\",\"Hp\":8.25,\"Score\":9600,\"Mass\":2,\"AngularDrag\":0.05,\"GravityScale\":1}"},{"ID":45,"Type":"Brick","Position":"3.766,-2.984,0","Rotation":"0,0,0","Scale":"0.6,0.6,1","Json":"{\"Type\":0,\"Tag\":\"WoodObject\",\"Hp\":8.25,\"Score\":9550,\"Mass\":2,\"AngularDrag\":0.05,\"GravityScale\":1}"},{"ID":46,"Type":"Brick","Position":"3.346,-2.984,0","Rotation":"0,0,0","Scale":"0.6,0.6,1","Json":"{\"Type\":0,\"Tag\":\"WoodObject\",\"Hp\":8.25,\"Score\":9550,\"Mass\":2,\"AngularDrag\":0.05,\"GravityScale\":1}"},{"ID":47,"Type":"Brick","Position":"0.1400001,-0.822,0","Rotation":"0,0,0","Scale":"0.6,0.6,1","Json":"{\"Type\":2,\"Tag\":\"WoodObject\",\"Hp\":8.25,\"Score\":9650,\"Mass\":2,\"AngularDrag\":0.05,\"GravityScale\":1}"},{"ID":48,"Type":"Brick","Position":"0.14,-1.014,0","Rotation":"0,0,0","Scale":"0.6,0.6,1","Json":"{\"Type\":2,\"Tag\":\"WoodObject\",\"Hp\":8.25,\"Score\":9650,\"Mass\":2,\"AngularDrag\":0.05,\"GravityScale\":1}"},{"ID":49,"Type":"Brick","Position":"-0.4060001,-1.314,0","Rotation":"0,0,0","Scale":"0.6,0.6,1","Json":"{\"Type\":6,\"Tag\":\"WoodObject\",\"Hp\":8.25,\"Score\":10000,\"Mass\":2,\"AngularDrag\":0.05,\"GravityScale\":1}"},{"ID":50,"Type":"Brick","Position":"-1.036,-1.404,0","Rotation":"0,0,0","Scale":"0.6,0.6,1","Json":"{\"Type\":1,\"Tag\":\"WoodObject\",\"Hp\":8.25,\"Score\":9600,\"Mass\":2,\"AngularDrag\":0.05,\"GravityScale\":1}"},{"ID":51,"Type":"Brick","Position":"-1.036,-1.176,0","Rotation":"0,0,0","Scale":"0.6,0.6,1","Json":"{\"Type\":1,\"Tag\":\"WoodObject\",\"Hp\":8.25,\"Score\":9600,\"Mass\":2,\"AngularDrag\":0.05,\"GravityScale\":1}"},{"ID":52,"Type":"Brick","Position":"-1.036,-0.948,0","Rotation":"0,0,0","Scale":"0.6,0.6,1","Json":"{\"Type\":1,\"Tag\":\"WoodObject\",\"Hp\":8.25,\"Score\":9600,\"Mass\":2,\"AngularDrag\":0.05,\"GravityScale\":1}"},{"ID":53,"Type":"Brick","Position":"-1.63,-2.946,0","Rotation":"0,0,0","Scale":"0.6,0.6,1","Json":"{\"Type\":6,\"Tag\":\"WoodObject\",\"Hp\":8.25,\"Score\":10000,\"Mass\":2,\"AngularDrag\":0.05,\"GravityScale\":1}"},{"ID":54,"Type":"Brick","Position":"-2.038,-2.946,0","Rotation":"0,0,0","Scale":"0.6,0.6,1","Json":"{\"Type\":6,\"Tag\":\"WoodObject\",\"Hp\":8.25,\"Score\":10000,\"Mass\":2,\"AngularDrag\":0.05,\"GravityScale\":1}"},{"ID":55,"Type":"Brick","Position":"-1.63,-2.538,0","Rotation":"0,0,0","Scale":"0.6,0.6,1","Json":"{\"Type\":6,\"Tag\":\"WoodObject\",\"Hp\":8.25,\"Score\":10000,\"Mass\":2,\"AngularDrag\":0.05,\"GravityScale\":1}"},{"ID":56,"Type":"Brick","Position":"-2.038,-2.538,0","Rotation":"0,0,0","Scale":"0.6,0.6,1","Json":"{\"Type\":6,\"Tag\":\"WoodObject\",\"Hp\":8.25,\"Score\":10000,\"Mass\":2,\"AngularDrag\":0.05,\"GravityScale\":1}"},{"ID":57,"Type":"Brick","Position":"-1.63,-2.13,0","Rotation":"0,0,0","Scale":"0.6,0.6,1","Json":"{\"Type\":6,\"Tag\":\"WoodObject\",\"Hp\":8.25,\"Score\":10000,\"Mass\":2,\"AngularDrag\":0.05,\"GravityScale\":1}"},{"ID":58,"Type":"Brick","Position":"-2.038,-2.13,0","Rotation":"0,0,0","Scale":"0.6,0.6,1","Json":"{\"Type\":6,\"Tag\":\"WoodObject\",\"Hp\":8.25,\"Score\":10000,\"Mass\":2,\"AngularDrag\":0.05,\"GravityScale\":1}"},{"ID":59,"Type":"Brick","Position":"-1.63,-1.722,0","Rotation":"0,0,0","Scale":"0.6,0.6,1","Json":"{\"Type\":6,\"Tag\":\"WoodObject\",\"Hp\":8.25,\"Score\":10000,\"Mass\":2,\"AngularDrag\":0.05,\"GravityScale\":1}"},{"ID":60,"Type":"Brick","Position":"-2.038,-1.722,0","Rotation":"0,0,0","Scale":"0.6,0.6,1","Json":"{\"Type\":6,\"Tag\":\"WoodObject\",\"Hp\":8.25,\"Score\":10000,\"Mass\":2,\"AngularDrag\":0.05,\"GravityScale\":1}"},{"ID":61,"Type":"Brick","Position":"-1.63,-1.314,0","Rotation":"0,0,0","Scale":"0.6,0.6,1","Json":"{\"Type\":6,\"Tag\":\"WoodObject\",\"Hp\":8.25,\"Score\":10000,\"Mass\":2,\"AngularDrag\":0.05,\"GravityScale\":1}"},{"ID":62,"Type":"Brick","Position":"-2.038,-1.314,0","Rotation":"0,0,0","Scale":"0.6,0.6,1","Json":"{\"Type\":6,\"Tag\":\"WoodObject\",\"Hp\":8.25,\"Score\":10000,\"Mass\":2,\"AngularDrag\":0.05,\"GravityScale\":1}"},{"ID":63,"Type":"Brick","Position":"-1.63,-0.906,0","Rotation":"0,0,0","Scale":"0.6,0.6,1","Json":"{\"Type\":6,\"Tag\":\"WoodObject\",\"Hp\":8.25,\"Score\":10000,\"Mass\":2,\"AngularDrag\":0.05,\"GravityScale\":1}"},{"ID":64,"Type":"Brick","Position":"-2.038,-0.906,0","Rotation":"0,0,0","Scale":"0.6,0.6,1","Json":"{\"Type\":6,\"Tag\":\"WoodObject\",\"Hp\":8.25,\"Score\":10000,\"Mass\":2,\"AngularDrag\":0.05,\"GravityScale\":1}"},{"ID":65,"Type":"Brick","Position":"-1.63,-0.498,0","Rotation":"0,0,0","Scale":"0.6,0.6,1","Json":"{\"Type\":6,\"Tag\":\"WoodObject\",\"Hp\":8.25,\"Score\":10000,\"Mass\":2,\"AngularDrag\":0.05,\"GravityScale\":1}"},{"ID":66,"Type":"Brick","Position":"-2.038,-0.498,0","Rotation":"0,0,0","Scale":"0.6,0.6,1","Json":"{\"Type\":6,\"Tag\":\"WoodObject\",\"Hp\":8.25,\"Score\":10000,\"Mass\":2,\"AngularDrag\":0.05,\"GravityScale\":1}"},{"ID":67,"Type":"Brick","Position":"-1.63,-0.09000003,0","Rotation":"0,0,0","Scale":"0.6,0.6,1","Json":"{\"Type\":6,\"Tag\":\"WoodObject\",\"Hp\":8.25,\"Score\":10000,\"Mass\":2,\"AngularDrag\":0.05,\"GravityScale\":1}"},{"ID":68,"Type":"Brick","Position":"-2.038,-0.09000003,0","Rotation":"0,0,0","Scale":"0.6,0.6,1","Json":"{\"Type\":6,\"Tag\":\"WoodObject\",\"Hp\":8.25,\"Score\":10000,\"Mass\":2,\"AngularDrag\":0.05,\"GravityScale\":1}"},{"ID":69,"Type":"Brick","Position":"-0.8140001,-0.6300001,0","Rotation":"0,0,0","Scale":"0.6,0.6,1","Json":"{\"Type\":6,\"Tag\":\"WoodObject\",\"Hp\":8.25,\"Score\":10000,\"Mass\":2,\"AngularDrag\":0.05,\"GravityScale\":1}"},{"ID":70,"Type":"Brick","Position":"-1.222,-0.6300001,0","Rotation":"0,0,0","Scale":"0.6,0.6,1","Json":"{\"Type\":6,\"Tag\":\"WoodObject\",\"Hp\":8.25,\"Score\":10000,\"Mass\":2,\"AngularDrag\":0.05,\"GravityScale\":1}"},{"ID":71,"Type":"Brick","Position":"-0.8140001,-0.222,0","Rotation":"0,0,0","Scale":"0.6,0.6,1","Json":"{\"Type\":6,\"Tag\":\"WoodObject\",\"Hp\":8.25,\"Score\":10000,\"Mass\":2,\"AngularDrag\":0.05,\"GravityScale\":1}"},{"ID":72,"Type":"Brick","Position":"-1.222,-0.222,0","Rotation":"0,0,0","Scale":"0.6,0.6,1","Json":"{\"Type\":6,\"Tag\":\"WoodObject\",\"Hp\":8.25,\"Score\":10000,\"Mass\":2,\"AngularDrag\":0.05,\"GravityScale\":1}"},{"ID":73,"Type":"Brick","Position":"-0.8140001,0.186,0","Rotation":"0,0,0","Scale":"0.6,0.6,1","Json":"{\"Type\":6,\"Tag\":\"WoodObject\",\"Hp\":8.25,\"Score\":10000,\"Mass\":2,\"AngularDrag\":0.05,\"GravityScale\":1}"},{"ID":74,"Type":"Brick","Position":"-1.222,0.186,0","Rotation":"0,0,0","Scale":"0.6,0.6,1","Json":"{\"Type\":6,\"Tag\":\"WoodObject\",\"Hp\":8.25,\"Score\":10000,\"Mass\":2,\"AngularDrag\":0.05,\"GravityScale\":1}"},{"ID":75,"Type":"Brick","Position":"-1.63,0.3180001,0","Rotation":"0,0,0","Scale":"0.6,0.6,1","Json":"{\"Type\":6,\"Tag\":\"WoodObject\",\"Hp\":8.25,\"Score\":10000,\"Mass\":2,\"AngularDrag\":0.05,\"GravityScale\":1}"},{"ID":76,"Type":"Brick","Position":"-2.038,0.3180001,0","Rotation":"0,0,0","Scale":"0.6,0.6,1","Json":"{\"Type\":6,\"Tag\":\"WoodObject\",\"Hp\":8.25,\"Score\":10000,\"Mass\":2,\"AngularDrag\":0.05,\"GravityScale\":1}"},{"ID":77,"Type":"Brick","Position":"-1.63,0.726,0","Rotation":"0,0,0","Scale":"0.6,0.6,1","Json":"{\"Type\":6,\"Tag\":\"WoodObject\",\"Hp\":8.25,\"Score\":10000,\"Mass\":2,\"AngularDrag\":0.05,\"GravityScale\":1}"},{"ID":78,"Type":"Brick","Position":"-2.038,0.726,0","Rotation":"0,0,0","Scale":"0.6,0.6,1","Json":"{\"Type\":6,\"Tag\":\"WoodObject\",\"Hp\":8.25,\"Score\":10000,\"Mass\":2,\"AngularDrag\":0.05,\"GravityScale\":1}"},{"ID":79,"Type":"Brick","Position":"1.004,-1.994,0","Rotation":"0,0,90","Scale":"0.6,0.6,1","Json":"{\"Type\":1,\"Tag\":\"WoodObject\",\"Hp\":8.25,\"Score\":9600,\"Mass\":2,\"AngularDrag\":0.05,\"GravityScale\":1}"},{"ID":80,"Type":"Brick","Position":"1.462,-1.994,0","Rotation":"0,0,90","Scale":"0.6,0.6,1","Json":"{\"Type\":1,\"Tag\":\"WoodObject\",\"Hp\":8.25,\"Score\":9600,\"Mass\":2,\"AngularDrag\":0.05,\"GravityScale\":1}"},{"ID":81,"Type":"Brick","Position":"1.234,-1.994,0","Rotation":"0,0,90","Scale":"0.6,0.6,1","Json":"{\"Type\":1,\"Tag\":\"WoodObject\",\"Hp\":8.25,\"Score\":9600,\"Mass\":2,\"AngularDrag\":0.05,\"GravityScale\":1}"},{"ID":82,"Type":"Brick","Position":"1.234,-2.726,0","Rotation":"0,0,0","Scale":"0.6,0.6,1","Json":"{\"Type\":1,\"Tag\":\"WoodObject\",\"Hp\":8.25,\"Score\":9600,\"Mass\":2,\"AngularDrag\":0.05,\"GravityScale\":1}"},{"ID":83,"Type":"Brick","Position":"1.452,-2.984,0","Rotation":"0,0,0","Scale":"0.6,0.6,1","Json":"{\"Type\":0,\"Tag\":\"WoodObject\",\"Hp\":8.25,\"Score\":9550,\"Mass\":2,\"AngularDrag\":0.05,\"GravityScale\":1}"},{"ID":84,"Type":"Brick","Position":"1.234,-2.498,0","Rotation":"0,0,0","Scale":"0.6,0.6,1","Json":"{\"Type\":1,\"Tag\":\"WoodObject\",\"Hp\":8.25,\"Score\":9600,\"Mass\":2,\"AngularDrag\":0.05,\"GravityScale\":1}"},{"ID":85,"Type":"Brick","Position":"1.032,-2.984,0","Rotation":"0,0,0","Scale":"0.6,0.6,1","Json":"{\"Type\":0,\"Tag\":\"WoodObject\",\"Hp\":8.25,\"Score\":9550,\"Mass\":2,\"AngularDrag\":0.05,\"GravityScale\":1}"},{"ID":86,"Type":"Brick","Position":"0.688,-0.138,0","Rotation":"0,0,0","Scale":"0.6,0.6,1","Json":"{\"Type\":6,\"Tag\":\"WoodObject\",\"Hp\":8.25,\"Score\":10000,\"Mass\":2,\"AngularDrag\":0.05,\"GravityScale\":1}"},{"ID":87,"Type":"Brick","Position":"0.28,-0.138,0","Rotation":"0,0,0","Scale":"0.6,0.6,1","Json":"{\"Type\":6,\"Tag\":\"WoodObject\",\"Hp\":8.25,\"Score\":10000,\"Mass\":2,\"AngularDrag\":0.05,\"GravityScale\":1}"},{"ID":88,"Type":"Brick","Position":"0.688,0.27,0","Rotation":"0,0,0","Scale":"0.6,0.6,1","Json":"{\"Type\":6,\"Tag\":\"WoodObject\",\"Hp\":8.25,\"Score\":10000,\"Mass\":2,\"AngularDrag\":0.05,\"GravityScale\":1}"},{"ID":89,"Type":"Brick","Position":"0.28,0.27,0","Rotation":"0,0,0","Scale":"0.6,0.6,1","Json":"{\"Type\":6,\"Tag\":\"WoodObject\",\"Hp\":8.25,\"Score\":10000,\"Mass\":2,\"AngularDrag\":0.05,\"GravityScale\":1}"},{"ID":90,"Type":"Brick","Position":"0.518,-2.946,0","Rotation":"0,0,0","Scale":"0.6,0.6,1","Json":"{\"Type\":6,\"Tag\":\"WoodObject\",\"Hp\":8.25,\"Score\":10000,\"Mass\":2,\"AngularDrag\":0.05,\"GravityScale\":1}"},{"ID":91,"Type":"Brick","Position":"0.1099999,-2.946,0","Rotation":"0,0,0","Scale":"0.6,0.6,1","Json":"{\"Type\":6,\"Tag\":\"WoodObject\",\"Hp\":8.25,\"Score\":10000,\"Mass\":2,\"AngularDrag\":0.05,\"GravityScale\":1}"},{"ID":92,"Type":"Brick","Position":"0.518,-2.538,0","Rotation":"0,0,0","Scale":"0.6,0.6,1","Json":"{\"Type\":6,\"Tag\":\"WoodObject\",\"Hp\":8.25,\"Score\":10000,\"Mass\":2,\"AngularDrag\":0.05,\"GravityScale\":1}"},{"ID":93,"Type":"Brick","Position":"0.1099999,-2.538,0","Rotation":"0,0,0","Scale":"0.6,0.6,1","Json":"{\"Type\":6,\"Tag\":\"WoodObject\",\"Hp\":8.25,\"Score\":10000,\"Mass\":2,\"AngularDrag\":0.05,\"GravityScale\":1}"},{"ID":94,"Type":"Brick","Position":"0.518,-2.13,0","Rotation":"0,0,0","Scale":"0.6,0.6,1","Json":"{\"Type\":6,\"Tag\":\"WoodObject\",\"Hp\":8.25,\"Score\":10000,\"Mass\":2,\"AngularDrag\":0.05,\"GravityScale\":1}"},{"ID":95,"Type":"Brick","Position":"0.1099999,-2.13,0","Rotation":"0,0,0","Scale":"0.6,0.6,1","Json":"{\"Type\":6,\"Tag\":\"WoodObject\",\"Hp\":8.25,\"Score\":10000,\"Mass\":2,\"AngularDrag\":0.05,\"GravityScale\":1}"},{"ID":96,"Type":"Brick","Position":"0.518,-1.722,0","Rotation":"0,0,0","Scale":"0.6,0.6,1","Json":"{\"Type\":6,\"Tag\":\"WoodObject\",\"Hp\":8.25,\"Score\":10000,\"Mass\":2,\"AngularDrag\":0.05,\"GravityScale\":1}"},{"ID":97,"Type":"Brick","Position":"0.1099999,-1.722,0","Rotation":"0,0,0","Scale":"0.6,0.6,1","Json":"{\"Type\":6,\"Tag\":\"WoodObject\",\"Hp\":8.25,\"Score\":10000,\"Mass\":2,\"AngularDrag\":0.05,\"GravityScale\":1}"},{"ID":98,"Type":"Brick","Position":"0.518,-1.314,0","Rotation":"0,0,0","Scale":"0.6,0.6,1","Json":"{\"Type\":6,\"Tag\":\"WoodObject\",\"Hp\":8.25,\"Score\":10000,\"Mass\":2,\"AngularDrag\":0.05,\"GravityScale\":1}"},{"ID":99,"Type":"Brick","Position":"0.11,-1.314,0","Rotation":"0,0,0","Scale":"0.6,0.6,1","Json":"{\"Type\":6,\"Tag\":\"WoodObject\",\"Hp\":8.25,\"Score\":10000,\"Mass\":2,\"AngularDrag\":0.05,\"GravityScale\":1}"},{"ID":100,"Type":"Brick","Position":"4.648,-2.946,0","Rotation":"0,0,0","Scale":"0.6,0.6,1","Json":"{\"Type\":6,\"Tag\":\"WoodObject\",\"Hp\":8.25,\"Score\":10000,\"Mass\":2,\"AngularDrag\":0.05,\"GravityScale\":1}"},{"ID":101,"Type":"Brick","Position":"4.24,-2.946,0","Rotation":"0,0,0","Scale":"0.6,0.6,1","Json":"{\"Type\":6,\"Tag\":\"WoodObject\",\"Hp\":8.25,\"Score\":10000,\"Mass\":2,\"AngularDrag\":0.05,\"GravityScale\":1}"},{"ID":102,"Type":"Brick","Position":"4.648,-2.538,0","Rotation":"0,0,0","Scale":"0.6,0.6,1","Json":"{\"Type\":6,\"Tag\":\"WoodObject\",\"Hp\":8.25,\"Score\":10000,\"Mass\":2,\"AngularDrag\":0.05,\"GravityScale\":1}"},{"ID":103,"Type":"Brick","Position":"4.24,-2.538,0","Rotation":"0,0,0","Scale":"0.6,0.6,1","Json":"{\"Type\":6,\"Tag\":\"WoodObject\",\"Hp\":8.25,\"Score\":10000,\"Mass\":2,\"AngularDrag\":0.05,\"GravityScale\":1}"},{"ID":104,"Type":"Brick","Position":"4.648,-2.13,0","Rotation":"0,0,0","Scale":"0.6,0.6,1","Json":"{\"Type\":6,\"Tag\":\"WoodObject\",\"Hp\":8.25,\"Score\":10000,\"Mass\":2,\"AngularDrag\":0.05,\"GravityScale\":1}"},{"ID":105,"Type":"Brick","Position":"4.24,-2.13,0","Rotation":"0,0,0","Scale":"0.6,0.6,1","Json":"{\"Type\":6,\"Tag\":\"WoodObject\",\"Hp\":8.25,\"Score\":10000,\"Mass\":2,\"AngularDrag\":0.05,\"GravityScale\":1}"},{"ID":106,"Type":"Brick","Position":"4.648,-1.722,0","Rotation":"0,0,0","Scale":"0.6,0.6,1","Json":"{\"Type\":6,\"Tag\":\"WoodObject\",\"Hp\":8.25,\"Score\":10000,\"Mass\":2,\"AngularDrag\":0.05,\"GravityScale\":1}"},{"ID":107,"Type":"Brick","Position":"4.24,-1.722,0","Rotation":"0,0,0","Scale":"0.6,0.6,1","Json":"{\"Type\":6,\"Tag\":\"WoodObject\",\"Hp\":8.25,\"Score\":10000,\"Mass\":2,\"AngularDrag\":0.05,\"GravityScale\":1}"},{"ID":108,"Type":"Brick","Position":"4.648,-1.314,0","Rotation":"0,0,0","Scale":"0.6,0.6,1","Json":"{\"Type\":6,\"Tag\":\"WoodObject\",\"Hp\":8.25,\"Score\":10000,\"Mass\":2,\"AngularDrag\":0.05,\"GravityScale\":1}"},{"ID":109,"Type":"Brick","Position":"4.24,-1.314,0","Rotation":"0,0,0","Scale":"0.6,0.6,1","Json":"{\"Type\":6,\"Tag\":\"WoodObject\",\"Hp\":8.25,\"Score\":10000,\"Mass\":2,\"AngularDrag\":0.05,\"GravityScale\":1}"},{"ID":110,"Type":"Brick","Position":"1.488,0.87,0","Rotation":"0,0,0","Scale":"0.6,0.6,1","Json":"{\"Type\":6,\"Tag\":\"WoodObject\",\"Hp\":8.25,\"Score\":10000,\"Mass\":2,\"AngularDrag\":0.05,\"GravityScale\":1}"},{"ID":111,"Type":"Brick","Position":"1.488,1.278,0","Rotation":"0,0,0","Scale":"0.6,0.6,1","Json":"{\"Type\":6,\"Tag\":\"WoodObject\",\"Hp\":8.25,\"Score\":10000,\"Mass\":2,\"AngularDrag\":0.05,\"GravityScale\":1}"},{"ID":112,"Type":"Brick","Position":"3.276,0.87,0","Rotation":"0,0,0","Scale":"0.6,0.6,1","Json":"{\"Type\":6,\"Tag\":\"WoodObject\",\"Hp\":8.25,\"Score\":10000,\"Mass\":2,\"AngularDrag\":0.05,\"GravityScale\":1}"},{"ID":113,"Type":"Brick","Position":"3.276,1.278,0","Rotation":"0,0,0","Scale":"0.6,0.6,1","Json":"{\"Type\":6,\"Tag\":\"WoodObject\",\"Hp\":8.25,\"Score\":10000,\"Mass\":2,\"AngularDrag\":0.05,\"GravityScale\":1}"},{"ID":114,"Type":"Brick","Position":"2.382,0.074,0","Rotation":"0,0,0","Scale":"0.6,0.6,1","Json":"{\"Type\":1,\"Tag\":\"WoodObject\",\"Hp\":8.25,\"Score\":9600,\"Mass\":2,\"AngularDrag\":0.05,\"GravityScale\":1}"},{"ID":115,"Type":"Brick","Position":"1.843,-0.522,0","Rotation":"0,0,0","Scale":"0.6,0.6,1","Json":"{\"Type\":6,\"Tag\":\"WoodObject\",\"Hp\":8.25,\"Score\":10000,\"Mass\":2,\"AngularDrag\":0.05,\"GravityScale\":1}"},{"ID":116,"Type":"Brick","Position":"2.937,-0.522,0","Rotation":"0,0,0","Scale":"0.6,0.6,1","Json":"{\"Type\":6,\"Tag\":\"WoodObject\",\"Hp\":8.25,\"Score\":10000,\"Mass\":2,\"AngularDrag\":0.05,\"GravityScale\":1}"},{"ID":117,"Type":"Brick","Position":"1.836,0.876,0","Rotation":"0,0,90","Scale":"0.6,0.6,1","Json":"{\"Type\":0,\"Tag\":\"WoodObject\",\"Hp\":8.25,\"Score\":9550,\"Mass\":2,\"AngularDrag\":0.05,\"GravityScale\":1}"},{"ID":118,"Type":"Brick","Position":"2.928,0.876,0","Rotation":"0,0,90","Scale":"0.6,0.6,1","Json":"{\"Type\":0,\"Tag\":\"WoodObject\",\"Hp\":8.25,\"Score\":9550,\"Mass\":2,\"AngularDrag\":0.05,\"GravityScale\":1}"},{"ID":119,"Type":"Brick","Position":"2.382,0.332,0","Rotation":"0,0,0","Scale":"0.6,0.6,1","Json":"{\"Type\":0,\"Tag\":\"WoodObject\",\"Hp\":8.25,\"Score\":9550,\"Mass\":2,\"AngularDrag\":0.05,\"GravityScale\":1}"},{"ID":120,"Type":"Brick","Position":"2.389,-1.4,0","Rotation":"0,0,0","Scale":"0.6,0.6,1","Json":"{\"Type\":2,\"Tag\":\"WoodObject\",\"Hp\":8.25,\"Score\":9650,\"Mass\":2,\"AngularDrag\":0.05,\"GravityScale\":1}"},{"ID":121,"Type":"Brick","Position":"2.251,-2.238,0","Rotation":"0,0,0","Scale":"0.6,0.6,1","Json":"{\"Type\":6,\"Tag\":\"WoodObject\",\"Hp\":8.25,\"Score\":10000,\"Mass\":2,\"AngularDrag\":0.05,\"GravityScale\":1}"},{"ID":122,"Type":"Brick","Position":"2.599,-2.232,0","Rotation":"0,0,90","Scale":"0.6,0.6,1","Json":"{\"Type\":0,\"Tag\":\"WoodObject\",\"Hp\":8.25,\"Score\":9550,\"Mass\":2,\"AngularDrag\":0.05,\"GravityScale\":1}"},{"ID":123,"Type":"Brick","Position":"2.539,-1.818,0","Rotation":"0,0,0","Scale":"0.6,0.6,1","Json":"{\"Type\":6,\"Tag\":\"WoodObject\",\"Hp\":8.25,\"Score\":10000,\"Mass\":2,\"AngularDrag\":0.05,\"GravityScale\":1}"},{"ID":124,"Type":"Brick","Position":"2.191,-1.812,0","Rotation":"0,0,90","Scale":"0.6,0.6,1","Json":"{\"Type\":0,\"Tag\":\"WoodObject\",\"Hp\":8.25,\"Score\":9550,\"Mass\":2,\"AngularDrag\":0.05,\"GravityScale\":1}"},{"ID":125,"Type":"Brick","Position":"6.002,-2.946,0","Rotation":"0,0,0","Scale":"0.6,0.6,1","Json":"{\"Type\":6,\"Tag\":\"StoneObject\",\"Hp\":16.5,\"Score\":20000,\"Mass\":3,\"AngularDrag\":0.05,\"GravityScale\":1}"},{"ID":126,"Type":"Brick","Position":"5.594,-2.946,0","Rotation":"0,0,0","Scale":"0.6,0.6,1","Json":"{\"Type\":6,\"Tag\":\"StoneObject\",\"Hp\":16.5,\"Score\":20000,\"Mass\":3,\"AngularDrag\":0.05,\"GravityScale\":1}"},{"ID":127,"Type":"Brick","Position":"6.002,-2.538,0","Rotation":"0,0,0","Scale":"0.6,0.6,1","Json":"{\"Type\":6,\"Tag\":\"StoneObject\",\"Hp\":16.5,\"Score\":20000,\"Mass\":3,\"AngularDrag\":0.05,\"GravityScale\":1}"},{"ID":128,"Type":"Brick","Position":"5.594,-2.538,0","Rotation":"0,0,0","Scale":"0.6,0.6,1","Json":"{\"Type\":6,\"Tag\":\"StoneObject\",\"Hp\":16.5,\"Score\":20000,\"Mass\":3,\"AngularDrag\":0.05,\"GravityScale\":1}"},{"ID":129,"Type":"Brick","Position":"6.002,-2.13,0","Rotation":"0,0,0","Scale":"0.6,0.6,1","Json":"{\"Type\":6,\"Tag\":\"StoneObject\",\"Hp\":16.5,\"Score\":20000,\"Mass\":3,\"AngularDrag\":0.05,\"GravityScale\":1}"},{"ID":130,"Type":"Brick","Position":"5.594,-2.13,0","Rotation":"0,0,0","Scale":"0.6,0.6,1","Json":"{\"Type\":6,\"Tag\":\"StoneObject\",\"Hp\":16.5,\"Score\":20000,\"Mass\":3,\"AngularDrag\":0.05,\"GravityScale\":1}"},{"ID":131,"Type":"Brick","Position":"6.002,-1.722,0","Rotation":"0,0,0","Scale":"0.6,0.6,1","Json":"{\"Type\":6,\"Tag\":\"StoneObject\",\"Hp\":16.5,\"Score\":20000,\"Mass\":3,\"AngularDrag\":0.05,\"GravityScale\":1}"},{"ID":132,"Type":"Brick","Position":"5.594,-1.722,0","Rotation":"0,0,0","Scale":"0.6,0.6,1","Json":"{\"Type\":6,\"Tag\":\"StoneObject\",\"Hp\":16.5,\"Score\":20000,\"Mass\":3,\"AngularDrag\":0.05,\"GravityScale\":1}"},{"ID":133,"Type":"Brick","Position":"5.186,-2.946,0","Rotation":"0,0,0","Scale":"0.6,0.6,1","Json":"{\"Type\":6,\"Tag\":\"StoneObject\",\"Hp\":16.5,\"Score\":20000,\"Mass\":3,\"AngularDrag\":0.05,\"GravityScale\":1}"},{"ID":134,"Type":"Brick","Position":"5.186,-2.538,0","Rotation":"0,0,0","Scale":"0.6,0.6,1","Json":"{\"Type\":6,\"Tag\":\"StoneObject\",\"Hp\":16.5,\"Score\":20000,\"Mass\":3,\"AngularDrag\":0.05,\"GravityScale\":1}"},{"ID":135,"Type":"Brick","Position":"5.186,-2.13,0","Rotation":"0,0,0","Scale":"0.6,0.6,1","Json":"{\"Type\":6,\"Tag\":\"StoneObject\",\"Hp\":16.5,\"Score\":20000,\"Mass\":3,\"AngularDrag\":0.05,\"GravityScale\":1}"},{"ID":136,"Type":"Brick","Position":"5.186,-1.722,0","Rotation":"0,0,0","Scale":"0.6,0.6,1","Json":"{\"Type\":6,\"Tag\":\"StoneObject\",\"Hp\":16.5,\"Score\":20000,\"Mass\":3,\"AngularDrag\":0.05,\"GravityScale\":1}"},{"ID":137,"Type":"Brick","Position":"4.292,-0.63,0","Rotation":"0,0,0","Scale":"0.6,0.6,1","Json":"{\"Type\":3,\"Tag\":\"StoneObject\",\"Hp\":16.5,\"Score\":19700,\"Mass\":3,\"AngularDrag\":0.05,\"GravityScale\":1}"},{"ID":138,"Type":"Brick","Position":"4.292,-0.438,0","Rotation":"0,0,0","Scale":"0.6,0.6,1","Json":"{\"Type\":3,\"Tag\":\"StoneObject\",\"Hp\":16.5,\"Score\":19700,\"Mass\":3,\"AngularDrag\":0.05,\"GravityScale\":1}"},{"ID":139,"Type":"Brick","Position":"-0.4060001,-2.946,0","Rotation":"0,0,0","Scale":"0.6,0.6,1","Json":"{\"Type\":6,\"Tag\":\"StoneObject\",\"Hp\":16.5,\"Score\":20000,\"Mass\":3,\"AngularDrag\":0.05,\"GravityScale\":1}"},{"ID":140,"Type":"Brick","Position":"-0.406,-2.538,0","Rotation":"0,0,0","Scale":"0.6,0.6,1","Json":"{\"Type\":6,\"Tag\":\"StoneObject\",\"Hp\":16.5,\"Score\":20000,\"Mass\":3,\"AngularDrag\":0.05,\"GravityScale\":1}"},{"ID":141,"Type":"Brick","Position":"-0.4060001,-2.13,0","Rotation":"0,0,0","Scale":"0.6,0.6,1","Json":"{\"Type\":6,\"Tag\":\"StoneObject\",\"Hp\":16.5,\"Score\":20000,\"Mass\":3,\"AngularDrag\":0.05,\"GravityScale\":1}"},{"ID":142,"Type":"Brick","Position":"-0.4060001,-1.722,0","Rotation":"0,0,0","Scale":"0.6,0.6,1","Json":"{\"Type\":6,\"Tag\":\"StoneObject\",\"Hp\":16.5,\"Score\":20000,\"Mass\":3,\"AngularDrag\":0.05,\"GravityScale\":1}"},{"ID":143,"Type":"Brick","Position":"-0.8140001,-2.946,0","Rotation":"0,0,0","Scale":"0.6,0.6,1","Json":"{\"Type\":6,\"Tag\":\"StoneObject\",\"Hp\":16.5,\"Score\":20000,\"Mass\":3,\"AngularDrag\":0.05,\"GravityScale\":1}"},{"ID":144,"Type":"Brick","Position":"-1.222,-2.946,0","Rotation":"0,0,0","Scale":"0.6,0.6,1","Json":"{\"Type\":6,\"Tag\":\"StoneObject\",\"Hp\":16.5,\"Score\":20000,\"Mass\":3,\"AngularDrag\":0.05,\"GravityScale\":1}"},{"ID":145,"Type":"Brick","Position":"-0.8140001,-2.538,0","Rotation":"0,0,0","Scale":"0.6,0.6,1","Json":"{\"Type\":6,\"Tag\":\"StoneObject\",\"Hp\":16.5,\"Score\":20000,\"Mass\":3,\"AngularDrag\":0.05,\"GravityScale\":1}"},{"ID":146,"Type":"Brick","Position":"-1.222,-2.538,0","Rotation":"0,0,0","Scale":"0.6,0.6,1","Json":"{\"Type\":6,\"Tag\":\"StoneObject\",\"Hp\":16.5,\"Score\":20000,\"Mass\":3,\"AngularDrag\":0.05,\"GravityScale\":1}"},{"ID":147,"Type":"Brick","Position":"-0.8140001,-2.13,0","Rotation":"0,0,0","Scale":"0.6,0.6,1","Json":"{\"Type\":6,\"Tag\":\"StoneObject\",\"Hp\":16.5,\"Score\":20000,\"Mass\":3,\"AngularDrag\":0.05,\"GravityScale\":1}"},{"ID":148,"Type":"Brick","Position":"-1.222,-2.13,0","Rotation":"0,0,0","Scale":"0.6,0.6,1","Json":"{\"Type\":6,\"Tag\":\"StoneObject\",\"Hp\":16.5,\"Score\":20000,\"Mass\":3,\"AngularDrag\":0.05,\"GravityScale\":1}"},{"ID":149,"Type":"Brick","Position":"-0.814,-1.722,0","Rotation":"0,0,0","Scale":"0.6,0.6,1","Json":"{\"Type\":6,\"Tag\":\"StoneObject\",\"Hp\":16.5,\"Score\":20000,\"Mass\":3,\"AngularDrag\":0.05,\"GravityScale\":1}"},{"ID":150,"Type":"Brick","Position":"-1.222,-1.722,0","Rotation":"0,0,0","Scale":"0.6,0.6,1","Json":"{\"Type\":6,\"Tag\":\"StoneObject\",\"Hp\":16.5,\"Score\":20000,\"Mass\":3,\"AngularDrag\":0.05,\"GravityScale\":1}"},{"ID":151,"Type":"Brick","Position":"0.488,-0.63,0","Rotation":"0,0,0","Scale":"0.6,0.6,1","Json":"{\"Type\":3,\"Tag\":\"StoneObject\",\"Hp\":16.5,\"Score\":19700,\"Mass\":3,\"AngularDrag\":0.05,\"GravityScale\":1}"},{"ID":152,"Type":"Brick","Position":"0.4879999,-0.438,0","Rotation":"0,0,0","Scale":"0.6,0.6,1","Json":"{\"Type\":3,\"Tag\":\"StoneObject\",\"Hp\":16.5,\"Score\":19700,\"Mass\":3,\"AngularDrag\":0.05,\"GravityScale\":1}"},{"ID":153,"Type":"Brick","Position":"1.504,-0.1380001,0","Rotation":"0,0,0","Scale":"0.6,0.6,1","Json":"{\"Type\":6,\"Tag\":\"StoneObject\",\"Hp\":16.5,\"Score\":20000,\"Mass\":3,\"AngularDrag\":0.05,\"GravityScale\":1}"},{"ID":154,"Type":"Brick","Position":"1.504,0.27,0","Rotation":"0,0,0","Scale":"0.6,0.6,1","Json":"{\"Type\":6,\"Tag\":\"StoneObject\",\"Hp\":16.5,\"Score\":20000,\"Mass\":3,\"AngularDrag\":0.05,\"GravityScale\":1}"},{"ID":155,"Type":"Brick","Position":"1.096,-0.1380001,0","Rotation":"0,0,0","Scale":"0.6,0.6,1","Json":"{\"Type\":6,\"Tag\":\"StoneObject\",\"Hp\":16.5,\"Score\":20000,\"Mass\":3,\"AngularDrag\":0.05,\"GravityScale\":1}"},{"ID":156,"Type":"Brick","Position":"1.096,0.2699999,0","Rotation":"0,0,0","Scale":"0.6,0.6,1","Json":"{\"Type\":6,\"Tag\":\"StoneObject\",\"Hp\":16.5,\"Score\":20000,\"Mass\":3,\"AngularDrag\":0.05,\"GravityScale\":1}"},{"ID":157,"Type":"Brick","Position":"3.684,-0.138,0","Rotation":"0,0,0","Scale":"0.6,0.6,1","Json":"{\"Type\":6,\"Tag\":\"StoneObject\",\"Hp\":16.5,\"Score\":20000,\"Mass\":3,\"AngularDrag\":0.05,\"GravityScale\":1}"},{"ID":158,"Type":"Brick","Position":"3.684,0.2700002,0","Rotation":"0,0,0","Scale":"0.6,0.6,1","Json":"{\"Type\":6,\"Tag\":\"StoneObject\",\"Hp\":16.5,\"Score\":20000,\"Mass\":3,\"AngularDrag\":0.05,\"GravityScale\":1}"},{"ID":159,"Type":"Brick","Position":"3.276,-0.138,0","Rotation":"0,0,0","Scale":"0.6,0.6,1","Json":"{\"Type\":6,\"Tag\":\"StoneObject\",\"Hp\":16.5,\"Score\":20000,\"Mass\":3,\"AngularDrag\":0.05,\"GravityScale\":1}"},{"ID":160,"Type":"Brick","Position":"3.276,0.27,0","Rotation":"0,0,0","Scale":"0.6,0.6,1","Json":"{\"Type\":6,\"Tag\":\"StoneObject\",\"Hp\":16.5,\"Score\":20000,\"Mass\":3,\"AngularDrag\":0.05,\"GravityScale\":1}"},{"ID":161,"Type":"Brick","Position":"2.382,0.57,0","Rotation":"0,0,0","Scale":"0.6,0.6,1","Json":"{\"Type\":3,\"Tag\":\"StoneObject\",\"Hp\":16.5,\"Score\":19700,\"Mass\":3,\"AngularDrag\":0.05,\"GravityScale\":1}"},{"ID":162,"Type":"Brick","Position":"2.382,1.578,0","Rotation":"0,0,0","Scale":"0.6,0.6,1","Json":"{\"Type\":3,\"Tag\":\"StoneObject\",\"Hp\":16.5,\"Score\":19700,\"Mass\":3,\"AngularDrag\":0.05,\"GravityScale\":1}"},{"ID":163,"Type":"Brick","Position":"3.14,-0.822,0","Rotation":"0,0,0","Scale":"0.6,0.6,1","Json":"{\"Type\":2,\"Tag\":\"StoneObject\",\"Hp\":16.5,\"Score\":19650,\"Mass\":3,\"AngularDrag\":0.05,\"GravityScale\":1}"},{"ID":164,"Type":"Brick","Position":"1.64,-0.822,0","Rotation":"0,0,0","Scale":"0.6,0.6,1","Json":"{\"Type\":2,\"Tag\":\"StoneObject\",\"Hp\":16.5,\"Score\":19650,\"Mass\":3,\"AngularDrag\":0.05,\"GravityScale\":1}"},{"ID":165,"Type":"Brick","Position":"1.843,-2.924,0","Rotation":"0,0,0","Scale":"0.6,0.6,1","Json":"{\"Type\":6,\"Tag\":\"StoneObject\",\"Hp\":16.5,\"Score\":20000,\"Mass\":3,\"AngularDrag\":0.05,\"GravityScale\":1}"},{"ID":166,"Type":"Brick","Position":"1.843,-2.516,0","Rotation":"0,0,0","Scale":"0.6,0.6,1","Json":"{\"Type\":6,\"Tag\":\"StoneObject\",\"Hp\":16.5,\"Score\":20000,\"Mass\":3,\"AngularDrag\":0.05,\"GravityScale\":1}"},{"ID":167,"Type":"Brick","Position":"1.843,-2.108,0","Rotation":"0,0,0","Scale":"0.6,0.6,1","Json":"{\"Type\":6,\"Tag\":\"StoneObject\",\"Hp\":16.5,\"Score\":20000,\"Mass\":3,\"AngularDrag\":0.05,\"GravityScale\":1}"},{"ID":168,"Type":"Brick","Position":"1.843,-1.7,0","Rotation":"0,0,0","Scale":"0.6,0.6,1","Json":"{\"Type\":6,\"Tag\":\"StoneObject\",\"Hp\":16.5,\"Score\":20000,\"Mass\":3,\"AngularDrag\":0.05,\"GravityScale\":1}"},{"ID":169,"Type":"Brick","Position":"2.937,-2.924,0","Rotation":"0,0,0","Scale":"0.6,0.6,1","Json":"{\"Type\":6,\"Tag\":\"StoneObject\",\"Hp\":16.5,\"Score\":20000,\"Mass\":3,\"AngularDrag\":0.05,\"GravityScale\":1}"},{"ID":170,"Type":"Brick","Position":"2.937,-2.516,0","Rotation":"0,0,0","Scale":"0.6,0.6,1","Json":"{\"Type\":6,\"Tag\":\"StoneObject\",\"Hp\":16.5,\"Score\":20000,\"Mass\":3,\"AngularDrag\":0.05,\"GravityScale\":1}"},{"ID":171,"Type":"Brick","Position":"2.937,-2.108,0","Rotation":"0,0,0","Scale":"0.6,0.6,1","Json":"{\"Type\":6,\"Tag\":\"StoneObject\",\"Hp\":16.5,\"Score\":20000,\"Mass\":3,\"AngularDrag\":0.05,\"GravityScale\":1}"},{"ID":172,"Type":"Brick","Position":"2.937,-1.7,0","Rotation":"0,0,0","Scale":"0.6,0.6,1","Json":"{\"Type\":6,\"Tag\":\"StoneObject\",\"Hp\":16.5,\"Score\":20000,\"Mass\":3,\"AngularDrag\":0.05,\"GravityScale\":1}"},{"ID":173,"Type":"Brick","Position":"1.843,-1.1,0","Rotation":"0,0,0","Scale":"0.6,0.6,1","Json":"{\"Type\":6,\"Tag\":\"StoneObject\",\"Hp\":16.5,\"Score\":20000,\"Mass\":3,\"AngularDrag\":0.05,\"GravityScale\":1}"},{"ID":174,"Type":"Brick","Position":"2.937,-1.1,0","Rotation":"0,0,0","Scale":"0.6,0.6,1","Json":"{\"Type\":6,\"Tag\":\"StoneObject\",\"Hp\":16.5,\"Score\":20000,\"Mass\":3,\"AngularDrag\":0.05,\"GravityScale\":1}"},{"ID":175,"Type":"Brick","Position":"2.389,-1.1,0","Rotation":"0,0,0","Scale":"0.6,0.6,1","Json":"{\"Type\":6,\"Tag\":\"StoneObject\",\"Hp\":16.5,\"Score\":20000,\"Mass\":3,\"AngularDrag\":0.05,\"GravityScale\":1}"},{"ID":176,"Type":"Monkey","Position":"-7.3,-2,0","Rotation":"0,0,0","Scale":"0.8,0.8,1","Json":"{\"Type\":0}"},{"ID":177,"Type":"Monkey","Position":"-8,-2,0","Rotation":"0,0,0","Scale":"0.8,0.8,1","Json":"{\"Type\":0}"},{"ID":178,"Type":"Monkey","Position":"-9.4,-2,0","Rotation":"0,0,0","Scale":"0.8,0.8,1","Json":"{\"Type\":0}"},{"ID":179,"Type":"Monkey","Position":"-6.6,-2,0","Rotation":"0,0,0","Scale":"0.8,0.8,1","Json":"{\"Type\":2}"},{"ID":180,"Type":"Monkey","Position":"-8.7,-2,0","Rotation":"0,0,0","Scale":"0.8,0.8,1","Json":"{\"Type\":3}"},{"ID":181,"Type":"Monkey","Position":"-10.1,-2,0","Rotation":"0,0,0","Scale":"0.8,0.8,1","Json":"{\"Type\":4}"},{"ID":182,"Type":"Monkey","Position":"-10.8,-2,0","Rotation":"0,0,0","Scale":"1,1,1","Json":"{\"Type\":7}"},{"ID":183,"Type":"Monkey","Position":"-11.5,-2,0","Rotation":"0,0,0","Scale":"0.8,0.8,1","Json":"{\"Type\":4}"},{"ID":184,"Type":"Bonus","Position":"6.89,0.81,0","Rotation":"0,0,0","Scale":"0.85,0.85,1","Json":"{}"},{"ID":185,"Type":"Bonus","Position":"0.46,2.01,0","Rotation":"0,0,0","Scale":"0.85,0.85,1","Json":"{}"},{"ID":186,"Type":"Bonus","Position":"-3.17,-2.62,0","Rotation":"0,0,0","Scale":"0.85,0.85,1","Json":"{}"},{"ID":187,"Type":"Banana","Position":"-0.267,0.00099987,0","Rotation":"0,0,0","Scale":"0.7,0.7,1","Json":"{\"Type\":0,\"Hp\":3}"},{"ID":188,"Type":"Banana","Position":"2.39,-2.785,0","Rotation":"0,0,0","Scale":"0.7,0.7,1","Json":"{\"Type\":2,\"Hp\":17}"},{"ID":189,"Type":"Banana","Position":"1.233,-1.261,0","Rotation":"0,0,0","Scale":"0.7,0.7,1","Json":"{\"Type\":2,\"Hp\":17}"},{"ID":190,"Type":"Banana","Position":"-1.083,0.733,0","Rotation":"0,0,0","Scale":"0.7,0.7,1","Json":"{\"Type\":1,\"Hp\":12}"},{"ID":191,"Type":"Banana","Position":"0.941,0.817,0","Rotation":"0,0,0","Scale":"0.7,0.7,1","Json":"{\"Type\":1,\"Hp\":12}"},{"ID":192,"Type":"Banana","Position":"5.047,0.0010002,0","Rotation":"0,0,0","Scale":"0.7,0.7,1","Json":"{\"Type\":0,\"Hp\":3}"},{"ID":193,"Type":"Banana","Position":"2.382,1.009,0","Rotation":"0,0,0","Scale":"0.7,0.7,1","Json":"{\"Type\":0,\"Hp\":3}"},{"ID":194,"Type":"Banana","Position":"3.547,-1.261,0","Rotation":"0,0,0","Scale":"0.7,0.7,1","Json":"{\"Type\":2,\"Hp\":17}"},{"ID":195,"Type":"Banana","Position":"2.39,-0.383,0","Rotation":"0,0,0","Scale":"0.7,0.7,1","Json":"{\"Type\":0,\"Hp\":3}"},{"ID":196,"Type":"Banana","Position":"3.823,0.817,0","Rotation":"0,0,0","Scale":"0.7,0.7,1","Json":"{\"Type\":1,\"Hp\":12}"},{"ID":197,"Type":"Shooter","Position":"-5.8,-1.45,0","Rotation":"","Scale":"","Json":""}]}